README.md
setup.cfg
setup.py
reusablesbyreme/__init__.py
reusablesbyreme/clean.py
reusablesbyreme.egg-info/PKG-INFO
reusablesbyreme.egg-info/SOURCES.txt
reusablesbyreme.egg-info/dependency_links.txt
reusablesbyreme.egg-info/requires.txt
reusablesbyreme.egg-info/top_level.txt