Metadata-Version: 2.1
Name: reusablesbyreme
Version: 0.0.2
Summary: Reusables functions for data science projects
Home-page: https://github.com/RemeAjayi/reusablesbyreme/
Author: Reme Ajayi
Author-email: remeajayi@gmail.com
License: MIT
Download-URL: https://github.com/RemeAjayi/reusablesbyreme/archive/refs/tags/0.0.2.tar.gz
Project-URL: Bug Tracker, https://github.com/RemeAjayi/reusablesbyreme/issues
Keywords: pypi,reusables,data science,pandas
Platform: UNKNOWN
Classifier: Development Status :: 3 - Alpha
Classifier: Intended Audience :: Developers
Classifier: Topic :: Software Development :: Documentation
Classifier: License :: OSI Approved :: MIT License
Classifier: Programming Language :: Python :: 3
Classifier: Programming Language :: Python :: 3.7
Classifier: Programming Language :: Python :: 3.8
Classifier: Programming Language :: Python :: 3.9
